LICENSE
MANIFEST.in
README.rst
setup.cfg
setup.py
redmine_migrator/__init__.py
redmine_migrator.egg-info/PKG-INFO
redmine_migrator.egg-info/SOURCES.txt
redmine_migrator.egg-info/dependency_links.txt
redmine_migrator.egg-info/entry_points.txt
redmine_migrator.egg-info/requires.txt
redmine_migrator.egg-info/top_level.txt