Metadata-Version: 1.1
Name: redmine-migrator
Version: 0.3
Summary: Migrate Redmine data from SQLite to Postgres with consistent type conversion.
Home-page: https://redmine-migrator.readthedocs.org/en/latest/
Author: Maxim Avanov
Author-email: maxim.avanov@gmail.com
License: MIT
Download-URL: https://github.com/avanov/redmine_migrator
Keywords: cli utils redmine migrate sqlite postgres
Platform: UNKNOWN
Classifier: Development Status :: 5 - Production/Stable
Classifier: Environment :: Console
Classifier: License :: OSI Approved
Classifier: License :: OSI Approved :: MIT License
Classifier: Operating System :: MacOS
Classifier: Operating System :: Microsoft
Classifier: Operating System :: POSIX
Classifier: Programming Language :: Python
Classifier: Programming Language :: Python :: 2.7
Classifier: Programming Language :: Python :: 3
